app.py
claude/__init__.py
claude/claude_agent.py
claude_sdk_tutor-0.1.4.dist-info/METADATA
claude_sdk_tutor-0.1.4.dist-info/WHEEL
claude_sdk_tutor-0.1.4.dist-info/entry_points.txt
claude_sdk_tutor-0.1.4.dist-info/licenses/LICENSE
claude_sdk_tutor-0.1.4.dist-info/RECORD
