Metadata-Version: 2.4
Name: claude-sdk-tutor
Version: 0.1.4
Summary: Add your description here
License-File: LICENSE
Requires-Python: >=3.13
Requires-Dist: claude-agent-sdk>=0.1.26
Requires-Dist: textual-dev>=1.8.0
Requires-Dist: textual>=7.5.0
Requires-Dist: watchfiles>=1.1.1
